function2widgets/__init__.py
function2widgets/common.py
function2widgets/factory.py
function2widgets/info.py
function2widgets/parser/__init__.py
function2widgets/parser/docstr_parser.py
function2widgets/parser/function_parser.py
function2widgets/parser/parameter_parser.py
function2widgets/parser/widgetconfigs_parser.py
function2widgets/widget.py
function2widgets/widgets/__init__.py
function2widgets/widgets/_sourcecodeedit.py
function2widgets/widgets/allwidgets.py
function2widgets/widgets/base.py
function2widgets/widgets/editor/__init__.py
function2widgets/widgets/editor/base.py
function2widgets/widgets/editor/codeeditor.py
function2widgets/widgets/editor/dicteditor.py
function2widgets/widgets/editor/jsoneditor.py
function2widgets/widgets/editor/listeditor.py
function2widgets/widgets/editor/tupleeditor.py
function2widgets/widgets/lineedit/__init__.py
function2widgets/widgets/lineedit/floatedit.py
function2widgets/widgets/lineedit/intedit.py
function2widgets/widgets/lineedit/stredit.py
function2widgets/widgets/misc/__init__.py
function2widgets/widgets/misc/coloredit.py
function2widgets/widgets/misc/dateedit.py
function2widgets/widgets/misc/datetimeedit.py
function2widgets/widgets/misc/timeedit.py
function2widgets/widgets/numberinput/__init__.py
function2widgets/widgets/numberinput/dial.py
function2widgets/widgets/numberinput/floatspin.py
function2widgets/widgets/numberinput/intspin.py
function2widgets/widgets/numberinput/slider.py
function2widgets/widgets/pathedit/__init__.py
function2widgets/widgets/pathedit/base.py
function2widgets/widgets/pathedit/dirpathedit.py
function2widgets/widgets/pathedit/filepathedit.py
function2widgets/widgets/selectwidget/__init__.py
function2widgets/widgets/selectwidget/checkbox.py
function2widgets/widgets/selectwidget/checkbox_group.py
function2widgets/widgets/selectwidget/combobox.py
function2widgets/widgets/selectwidget/combobox_edit.py
function2widgets/widgets/selectwidget/radiobutton_group.py
function2widgets-0.6.17.dist-info/License
function2widgets-0.6.17.dist-info/METADATA
function2widgets-0.6.17.dist-info/WHEEL
function2widgets-0.6.17.dist-info/RECORD
