Metadata-Version: 2.1
Name: function2widgets
Version: 0.6.17
Summary: 
Home-page: https://github.com/zimolab/function2widgets
License: GPL-3.0
Author: zimolab
Author-email: zimolab@aliyun.com
Requires-Python: >=3.8,<4.0
Classifier: License :: OSI Approved :: GNU General Public License v3 (GPLv3)
Classifier: Programming Language :: Python :: 3
Classifier: Programming Language :: Python :: 3.8
Classifier: Programming Language :: Python :: 3.9
Classifier: Programming Language :: Python :: 3.10
Classifier: Programming Language :: Python :: 3.11
Classifier: Programming Language :: Python :: 3.12
Requires-Dist: docstring-parser (>=0.16,<0.17)
Requires-Dist: pyqt6 (>=6.4.0,<6.6.1)
Requires-Dist: pyqt6-qscintilla (>=2.14.1,<3.0.0)
Requires-Dist: pyqt6-qt6 (>=6.4.0,<6.6.1)
Requires-Dist: tomli (>=2.0.1,<3.0.0)
Project-URL: Documentation, https://github.com/zimolab/function2widgets
Project-URL: Repository, https://github.com/zimolab/function2widgets
